gitleaks_py/__init__.py
gitleaks_py/cli.py
gitleaks_py/gitleaks_command.py
gitleaks_py/gitleaks_diff.py
gitleaks_py/gitleaks_merge.py
gitleaks_py/gitleaks_model.py
gitleaks_py/gitleaks_r.py
gitleaks_py/gitleaks_sort.py
gitleaks_py/gitleaks_verify.py
gitleaks_py/gitleaks_w.py
gitleaks_py-0.3.1.dist-info/WHEEL
gitleaks_py-0.3.1.dist-info/METADATA
gitleaks_py-0.3.1.dist-info/RECORD
